konduktor/__init__.py
konduktor/adaptors/__init__.py
konduktor/adaptors/aws.py
konduktor/adaptors/common.py
konduktor/adaptors/gcp.py
konduktor/authentication.py
konduktor/backends/__init__.py
konduktor/backends/backend.py
konduktor/backends/constants.py
konduktor/backends/deployment.py
konduktor/backends/deployment_utils.py
konduktor/backends/jobset.py
konduktor/backends/jobset_utils.py
konduktor/backends/pod_utils.py
konduktor/check.py
konduktor/cli.py
konduktor/config.py
konduktor/constants.py
konduktor/controller/__init__.py
konduktor/controller/constants.py
konduktor/controller/launch.py
konduktor/controller/node.py
konduktor/controller/parse.py
konduktor/dashboard/README.md
konduktor/dashboard/backend/main.py
konduktor/dashboard/backend/sockets.py
konduktor/dashboard/frontend/.eslintrc.json
konduktor/dashboard/frontend/.gitignore
konduktor/dashboard/frontend/app/api/jobs/route.js
konduktor/dashboard/frontend/app/api/namespaces/route.js
konduktor/dashboard/frontend/app/components/Grafana.jsx
konduktor/dashboard/frontend/app/components/JobsData.jsx
konduktor/dashboard/frontend/app/components/LogsData.jsx
konduktor/dashboard/frontend/app/components/NavMenu.jsx
konduktor/dashboard/frontend/app/components/NavTabs.jsx
konduktor/dashboard/frontend/app/components/NavTabs2.jsx
konduktor/dashboard/frontend/app/components/SelectBtn.jsx
konduktor/dashboard/frontend/app/components/lib/utils.js
konduktor/dashboard/frontend/app/components/ui/chip-select.jsx
konduktor/dashboard/frontend/app/components/ui/input.jsx
konduktor/dashboard/frontend/app/components/ui/navigation-menu.jsx
konduktor/dashboard/frontend/app/components/ui/select.jsx
konduktor/dashboard/frontend/app/favicon.ico
konduktor/dashboard/frontend/app/globals.css
konduktor/dashboard/frontend/app/jobs/page.js
konduktor/dashboard/frontend/app/layout.js
konduktor/dashboard/frontend/app/logs/page.js
konduktor/dashboard/frontend/app/page.js
konduktor/dashboard/frontend/jsconfig.json
konduktor_nightly-0.1.0.dev20260201105619.dist-info/LICENSE
konduktor_nightly-0.1.0.dev20260201105619.dist-info/METADATA
konduktor_nightly-0.1.0.dev20260201105619.dist-info/WHEEL
konduktor_nightly-0.1.0.dev20260201105619.dist-info/entry_points.txt
konduktor_nightly-0.1.0.dev20260201105619.dist-info/RECORD
