Metadata-Version: 2.3
Name: konduktor-nightly
Version: 0.1.0.dev20260201105619
Summary: GPU Cluster Health Management
Author: Andrew Aikawa
Author-email: asai@berkeley.edu
Requires-Python: >=3.9,<4.0
Classifier: Programming Language :: Python :: 3
Classifier: Programming Language :: Python :: 3.9
Classifier: Programming Language :: Python :: 3.10
Classifier: Programming Language :: Python :: 3.11
Classifier: Programming Language :: Python :: 3.12
Classifier: Programming Language :: Python :: 3.13
Provides-Extra: s3
Requires-Dist: awscli[s3] (>=1.32.84,<2.0.0) ; extra == "s3"
Requires-Dist: boto3[s3] (>=1.34.84,<2.0.0) ; extra == "s3"
Requires-Dist: botocore[s3] (>=1.34.84,<2.0.0) ; extra == "s3"
Requires-Dist: click (>=8.1.7,<9.0.0)
Requires-Dist: colorama (>=0.4.6,<0.5.0)
Requires-Dist: filelock (>=3.18.0,<4.0.0)
Requires-Dist: google-api-python-client[gcp] (>=2.161.0,<3.0.0)
Requires-Dist: google-cloud-storage[gcp] (>=3.0.0,<4.0.0)
Requires-Dist: jinja2 (>=3.1.5,<4.0.0)
Requires-Dist: jsonschema (>=4.23.0,<5.0.0)
Requires-Dist: kr8s (>=0.20.1,<0.21.0)
Requires-Dist: kubernetes (>=30.1.0,<31.0.0)
Requires-Dist: posthog (>=3.7.4,<4.0.0)
Requires-Dist: prettytable (>=3.12.0,<4.0.0)
Requires-Dist: psutil (>=7.0.0,<8.0.0)
Requires-Dist: python-dotenv (>=1.0.1,<2.0.0)
Requires-Dist: rich (>=13.9.4,<14.0.0)
Requires-Dist: sniffio (>=1.3,<2.0)
Requires-Dist: websockets (>=15.0.1,<16.0.0)
